subsplease/__Init__.py
subsplease/release.py
subsplease/subsplease.py
subsplease.py-1.2.1.dist-info/LICENSE
subsplease.py-1.2.1.dist-info/METADATA
subsplease.py-1.2.1.dist-info/WHEEL
subsplease.py-1.2.1.dist-info/top_level.txt
subsplease.py-1.2.1.dist-info/RECORD
