Metadata-Version: 2.1
Name: subsplease.py
Version: 1.2.1
Summary: A simple and asynchronous wrapper for SubsPlease
Home-page: https://github.com/Normouse/subsplease.py
Author: Normouse
Author-email: m.normouse@outlook.com
Classifier: Programming Language :: Python :: 3
Classifier: License :: OSI Approved :: MIT License
Classifier: Operating System :: OS Independent
Requires-Python: >=3.9
License-File: LICENSE
